<?xml version="1.0" encoding="ISO-8859-1" ?> 
<TheBrainSimpleXML>
  <Tht id="55" name="&#20026;&#20160;&#20040; 0&#30340;&#38454;&#20056;&#31561;&#20110;1 ?" icon="" color="#009900" hint="&#21019;&#20316;&#30340;&#25991;&#31456;&#19982;&#32763;&#35793;&#30340;&#35270;&#39057;" pbv="1612631020676735"
    modificationDate="2019-3-2 &#19979;&#21320;6:37"
    authorName="94779"
    authorEmail="" />

  <Tht id="92" name="&#20854;&#20182;" icon="" color="" hint="" /> 
  <Tht id="62" name="&#20854;&#20182;" icon="" color="" hint="" /> 


  <Tht id="82" name="&#20195;&#25968;&#22522;&#26412;&#23450;&#29702;" icon="" color="#009900" hint="&#35270;&#39057;" /> 
  <Tht id="117" name="&#35753;&#20154;&#22256;&#24785;&#22855;&#28857;&#25351;&#30340;&#26159;?" icon="" color="#009900" hint="&#35270;&#39057;" /> 
  <Tht id="38" name="&#29992;&#36825;&#20010;&#31070;&#22855;&#30340;&#20845;&#36793;&#24418;&#24039;&#35760;&#19977;&#35282;&#20989;&#25968;" icon="" color="#009900" hint="&#21019;&#20316;&#30340;&#25991;&#31456;&#19982;&#32763;&#35793;&#30340;&#35270;&#39057;" /> 
  <Tht id="47" name="&#21160;&#30011;&#24102;&#20320;&#29702;&#35299;&#28857;&#31215;&#21644;&#21449;&#31215;" icon="" color="" hint="&#35270;&#39057;" /> 
  <Tht id="48" name="&#22797;&#25968;&#21450;&#22797;&#21464;&#20989;&#25968;&#30340;&#21160;&#30011;&#35299;&#26512;" icon="" color="#009900" hint="&#21019;&#20316;&#30340;&#25991;&#31456;&#19982;&#32763;&#35793;&#30340;&#35270;&#39057;" /> 
  <Tht id="114" name="&#33258;&#28982;&#25968;&#19982;&#30382;&#20122;&#35834;&#20844;&#29702;" icon="" color="#009900" hint="&#35270;&#39057;" /> 
  <Tht id="40" name="&#26368;&#32654;&#25968;&#23398;&#20844;&#24335;&#65306;&#27431;&#25289;&#24658;&#31561;&#24335;" icon="" color="#009900" hint="&#21019;&#20316;&#30340;&#25991;&#31456;&#19982;&#32763;&#35793;&#30340;&#35270;&#39057;" /> 

  <Link idA="92" idB="117" type="CHILD" /> 
  <Link idA="92" idB="82" type="CHILD" /> 
  <Link idA="92" idB="38" type="CHILD" /> 
  <Link idA="62" idB="40" type="CHILD" /> 
  <Link idA="62" idB="47" type="CHILD" /> 
  <Link idA="62" idB="48" type="CHILD" /> 
  <Link idA="62" idB="114" type="CHILD" /> 
  <Link idA="62" idB="55" type="PARENT" /> 
  <Link idA="92" idB="55" type="PARENT" /> 

  <Content href="thoughtData/55.html" />
</TheBrainSimpleXML>
